cnn_finetune_plus/__init__.py
cnn_finetune_plus/make_init_model.py
cnn_finetune_plus-0.0.2.dist-info/LICENSE
cnn_finetune_plus-0.0.2.dist-info/METADATA
cnn_finetune_plus-0.0.2.dist-info/WHEEL
cnn_finetune_plus-0.0.2.dist-info/top_level.txt
cnn_finetune_plus-0.0.2.dist-info/RECORD
