Metadata-Version: 2.1
Name: cnn-finetune-plus
Version: 0.0.2
Summary: A small example package
Home-page: UNKNOWN
Author: X
Author-email: X@X.com
License: UNKNOWN
Platform: UNKNOWN
Classifier: Programming Language :: Python :: 3
Classifier: License :: OSI Approved :: MIT License
Classifier: Operating System :: OS Independent
Requires-Dist: requests
Requires-Dist: torch
Requires-Dist: cnn-finetune
